.gitignore
.travis.yml
CHANGELOG.rst
INSTALL.rst
LICENSE.txt
README.rst
pylint.rc
setup.py
Profiling/Example.pdf
doc/Makefile
doc/big_picture.rst
doc/conf.py
doc/faq.rst
doc/gridWorld_learning.png
doc/gridworld_domain.png
doc/gridworld_performance.png
doc/gridworld_valfun.png
doc/index.rst
doc/install.rst
doc/make_agent.rst
doc/make_domain.rst
doc/make_policy.rst
doc/make_rep.rst
doc/overview.pdf
doc/overview.png
doc/pendulum_learning.png
doc/pendulum_plot.png
doc/rlpy_output.png
doc/tutorial.rst
doc/unittests.rst
doc/_static/ACL_logo.png
doc/_templates/layout.html
doc/api/acrobot.rst
doc/api/agent.rst
doc/api/bicycle.rst
doc/api/domain.rst
doc/api/domains_misc.rst
doc/api/experiment.rst
doc/api/finite_cartpole.rst
doc/api/index.rst
doc/api/infinite_cartpole.rst
doc/api/mdp_solver.rst
doc/api/policy.rst
doc/api/representation.rst
doc/api/runtools.rst
examples/bicycle/kifdd_triangle.py
examples/blocksworld/ggq-ifdd.py
examples/blocksworld/ggq-ifddkappa.py
examples/blocksworld/ggq-indep.py
examples/blocksworld/ggq-tile.py
examples/blocksworld/q-ifdd.py
examples/blocksworld/q-indep.py
examples/blocksworld/sarsa-ifdd.py
examples/blocksworld/sarsa-indep.py
examples/cartpole2d/ggq-ifdd.py
examples/cartpole2d/ggq-indep.py
examples/cartpole2d/ifdd.py
examples/cartpole2d/kifdd_gauss.py
examples/cartpole2d/kifdd_triangle.py
examples/cartpole2d/q-ifdd.py
examples/cartpole2d/q-indep.py
examples/cartpole2d/rbfs.py
examples/cartpole2d/sarsa-ifdd.py
examples/cartpole2d/sarsa-indep.py
examples/cartpole_modern/kifdd.py
examples/cartpole_orig/ifdd.py
examples/cartpole_orig/independent.py
examples/cartpole_orig/kifdd_gauss.py
examples/cartpole_orig/kifdd_triangle.py
examples/cartpole_orig/rbfs.py
examples/cartpole_orig/tabular.py
examples/fifty_chain/tabular.py
examples/gridworld/lspi.py
examples/gridworld/nac.py
examples/gridworld/policy_iteration.py
examples/gridworld/q-ifddk.py
examples/gridworld/trajectory_based_policy_iteration.py
rlpy.egg-info/PKG-INFO
rlpy.egg-info/SOURCES.txt
rlpy.egg-info/dependency_links.txt
rlpy.egg-info/requires.txt
rlpy.egg-info/top_level.txt
