Metadata-Version: 1.1
Name: rlpy
Version: 1.3.2
Summary: Value-Function-Based Reinforcement-Learning Library for Education and Research
Home-page: http://acl.mit.edu/rlpy/
Author: Christoph Dann
Author-email: cdann@cdann.de
License: BSD 3-clause
Platform: UNKNOWN
Classifier: Intended Audience :: Science/Research
Classifier: Intended Audience :: Developers
Classifier: License :: OSI Approved
Classifier: Programming Language :: C++
Classifier: Programming Language :: Python
Classifier: Topic :: Scientific/Engineering
Classifier: Operating System :: Microsoft :: Windows
Classifier: Operating System :: POSIX
Classifier: Operating System :: Unix
Classifier: Operating System :: MacOS
Classifier: Programming Language :: Python :: 2
Classifier: Programming Language :: Python :: 2.7
